Metadata-Version: 2.1
Name: alternative-lib
Version: 0.1.0
Summary: Python library for working with the Alternative platform.
Author: ALTERNATIVE
License: MIT
